pulumi_ionoscloud/__init__.py
pulumi_ionoscloud/_utilities.py
pulumi_ionoscloud/provider.py
pulumi_ionoscloud/pulumi-plugin.json
pulumi_ionoscloud/py.typed
pulumi_ionoscloud/alb/__init__.py
pulumi_ionoscloud/alb/_inputs.py
pulumi_ionoscloud/alb/balancer.py
pulumi_ionoscloud/alb/forwarding_rule.py
pulumi_ionoscloud/alb/get_balancer.py
pulumi_ionoscloud/alb/get_forwarding_rule.py
pulumi_ionoscloud/alb/outputs.py
pulumi_ionoscloud/apigateway/__init__.py
pulumi_ionoscloud/apigateway/_inputs.py
pulumi_ionoscloud/apigateway/apigateway.py
pulumi_ionoscloud/apigateway/get_apigateway.py
pulumi_ionoscloud/apigateway/get_route.py
pulumi_ionoscloud/apigateway/outputs.py
pulumi_ionoscloud/apigateway/route.py
pulumi_ionoscloud/autoscaling/__init__.py
pulumi_ionoscloud/autoscaling/_inputs.py
pulumi_ionoscloud/autoscaling/get_group.py
pulumi_ionoscloud/autoscaling/get_servers.py
pulumi_ionoscloud/autoscaling/group.py
pulumi_ionoscloud/autoscaling/outputs.py
pulumi_ionoscloud/cdn/__init__.py
pulumi_ionoscloud/cdn/_inputs.py
pulumi_ionoscloud/cdn/distribution.py
pulumi_ionoscloud/cdn/get_distribution.py
pulumi_ionoscloud/cdn/outputs.py
pulumi_ionoscloud/cert/__init__.py
pulumi_ionoscloud/cert/_inputs.py
pulumi_ionoscloud/cert/auto_certificate.py
pulumi_ionoscloud/cert/auto_certificate_provider.py
pulumi_ionoscloud/cert/certificate.py
pulumi_ionoscloud/cert/get_auto_certificate.py
pulumi_ionoscloud/cert/get_auto_certificate_provider.py
pulumi_ionoscloud/cert/get_certificate.py
pulumi_ionoscloud/cert/outputs.py
pulumi_ionoscloud/compute/__init__.py
pulumi_ionoscloud/compute/_inputs.py
pulumi_ionoscloud/compute/backup_unit.py
pulumi_ionoscloud/compute/balancer.py
pulumi_ionoscloud/compute/boot_device_selection.py
pulumi_ionoscloud/compute/crossconnect.py
pulumi_ionoscloud/compute/cube_server.py
pulumi_ionoscloud/compute/datacenter.py
pulumi_ionoscloud/compute/firewall.py
pulumi_ionoscloud/compute/get_backup_unit.py
pulumi_ionoscloud/compute/get_crossconnect.py
pulumi_ionoscloud-0.2.3.dist-info/METADATA
pulumi_ionoscloud-0.2.3.dist-info/WHEEL
pulumi_ionoscloud-0.2.3.dist-info/top_level.txt
pulumi_ionoscloud-0.2.3.dist-info/RECORD
